README.md
setup.py
mysql_pool/__init__.py
mysql_pool.egg-info/PKG-INFO
mysql_pool.egg-info/SOURCES.txt
mysql_pool.egg-info/dependency_links.txt
mysql_pool.egg-info/requires.txt
mysql_pool.egg-info/top_level.txt