Metadata-Version: 2.1
Name: mysql-pool
Version: 0.2
Summary: mysql_pool
Home-page: UNKNOWN
Author: bfzs
Author-email: ydf0509@sohu.com
Maintainer: ydf
Maintainer-email: ydf0509@sohu.com
License: BSD License
Keywords: mysql pool
Platform: all
Classifier: Development Status :: 4 - Beta
Classifier: Operating System :: OS Independent
Classifier: Intended Audience :: Developers
Classifier: License :: OSI Approved :: BSD License
Classifier: Programming Language :: Python
Classifier: Programming Language :: Python :: Implementation
Classifier: Programming Language :: Python :: 3.6
Classifier: Topic :: Software Development :: Libraries
